power_watcher/__init__.py
power_watcher/power_watcher.py
power_watcher-0.1.1.dist-info/LICENSE
power_watcher-0.1.1.dist-info/METADATA
power_watcher-0.1.1.dist-info/WHEEL
power_watcher-0.1.1.dist-info/top_level.txt
power_watcher-0.1.1.dist-info/RECORD
