Metadata-Version: 2.1
Name: power-watcher
Version: 0.1.1
Summary: Python3 context manager to log power consumption of any ML-pipeline running on a Nvidia-GPU.
Home-page: https://github.com/WGussev/PowerWatcher
Author: Poima
Author-email: author@example.com
License: UNKNOWN
Platform: UNKNOWN
Classifier: Programming Language :: Python :: 3
Classifier: License :: OSI Approved :: MIT License
Classifier: Operating System :: OS Independent
Requires-Python: >=3.6
Requires-Dist: pynvml (>=8.0.4)
